clumpy/__init__.py
clumpy/randomMapping.py
clumpy/tools.py
clumpy/allocation/__init__.py
clumpy/allocation/_allocation.py
clumpy/allocation/_dinamica.py
clumpy/allocation/_generalized_von_neumann.py
clumpy/allocation/_patcher.py
clumpy/allocation/_simple_unbiased.py
clumpy/allocation/old.build.py
clumpy/allocation/old.postproduction.py
clumpy/allocation/scenario.py
clumpy/calibration/__init__.py
clumpy/calibration/_calibration.py
clumpy/calibration/_kde.py
clumpy/calibration/_knn.py
clumpy/calibration/_naive_bayes.py
clumpy/calibration/discretization.py
clumpy/calibration/feature_selection.py
clumpy/calibration/naive_bayes.py
clumpy/calibration/patches.py
clumpy/definition/__init__.py
clumpy/definition/_case.py
clumpy/definition/_feature.py
clumpy/definition/_layer.py
clumpy/definition/_transition.py
clumpy/definition/data.py
clumpy/definition/explanatory_variable.py
clumpy/definition/transition.py
clumpy/discretization/__init__.py
clumpy/discretization/_discretization.py
clumpy/validation/__init__.py
clumpy/validation/confusion.py
clumpy/validation/elements.py
clumpy/validation/explanatory_variables.py
clumpy/validation/probabilities.py
clumpy-0.1.0.dist-info/LICENSE
clumpy-0.1.0.dist-info/METADATA
clumpy-0.1.0.dist-info/WHEEL
clumpy-0.1.0.dist-info/top_level.txt
clumpy-0.1.0.dist-info/RECORD
